AmazingQuant/__init__.py
AmazingQuant/constant.py
AmazingQuant/data_object.py
AmazingQuant/environment.py
AmazingQuant/analysis_center/event_analysis_engine.py
AmazingQuant/data_center/financial_data_to_MongoDB.py
AmazingQuant/data_center/get_data.py
AmazingQuant/data_center/market_data_daily_to_MongoDB.py
AmazingQuant/data_center/mongosconn.py
AmazingQuant/event_engine/__init__.py
AmazingQuant/event_engine/event_backtesting_analysis.py
AmazingQuant/event_engine/event_deal.py
AmazingQuant/event_engine/event_engine_base.py
AmazingQuant/event_engine/event_error.py
AmazingQuant/event_engine/event_log.py
AmazingQuant/event_engine/event_market.py
AmazingQuant/event_engine/event_order.py
AmazingQuant/event_engine/event_risk_management.py
AmazingQuant/event_engine/event_save_record.py
AmazingQuant/strategy_center/event_bar_engine.py
AmazingQuant/strategy_center/strategy.py
AmazingQuant/test/pyecharts_test.py
AmazingQuant/test/pymongo_test.py
AmazingQuant/trade_center/event_broker_engine.py
AmazingQuant/trade_center/event_mission_engine.py
AmazingQuant/trade_center/trade.py
AmazingQuant/utils/data_transfer.py
AmazingQuant/utils/generate_random_id.py
AmazingQuant/utils/performance_test.py
AmazingQuant-0.0.4.dist-info/DESCRIPTION.rst
AmazingQuant-0.0.4.dist-info/METADATA
AmazingQuant-0.0.4.dist-info/RECORD
AmazingQuant-0.0.4.dist-info/WHEEL
AmazingQuant-0.0.4.dist-info/metadata.json
AmazingQuant-0.0.4.dist-info/top_level.txt
example/test_strategy.py
