Metadata-Version: 2.0
Name: AmazingQuant
Version: 0.0.4
Summary: A quantitative trading solution based on Event-driven
Home-page: https://github.com/zhanggao2013/AmazingQuant
Author: gao
Author-email: 82045571@qq.com
License: MIT License
Platform: UNKNOWN
